modfree/__init__.py
modfree/__main__.py
modfree/analysis.py
modfree/constants_functions.py
modfree/data_format.py
modfree/generator.py
modfree/inputs.py
modfree/mf.py
modfree/mf_standard.py
modfree/modfree.py
modfree/outputs.py
modfree/parser.py
modfree/ploter.py
modfree/run_fit.py
modelfree_protein15n-0.0.7.dist-info/LICENSE
modelfree_protein15n-0.0.7.dist-info/METADATA
modelfree_protein15n-0.0.7.dist-info/WHEEL
modelfree_protein15n-0.0.7.dist-info/entry_points.txt
modelfree_protein15n-0.0.7.dist-info/top_level.txt
modelfree_protein15n-0.0.7.dist-info/RECORD
