Metadata-Version: 2.1
Name: modelfree-protein15n
Version: 0.0.7
Summary: Model free analysis of protein backbone amide 15N spin relaxation rates.
Home-page: https://github.com/VSchnapka/modelfree-protein15n.git
Author: Vincent Schnapka
Author-email: vincentschnapka@gmail.com
License: UNKNOWN
Platform: UNKNOWN
Classifier: Programming Language :: Python :: 3
Requires-Dist: numpy
Requires-Dist: scipy
Requires-Dist: lmfit
Requires-Dist: matplotlib
Requires-Dist: rich
Requires-Dist: tomli
Requires-Dist: seaborn
